{"game":"ck3","name":"Immersive v1.4.3","mods":[{"displayName":"Unofficial Patch","enabled":true,"position":0,"steamId":"2871648329"},{"displayName":"AI Legends Fix","enabled":true,"position":1,"steamId":"3598202721"},{"displayName":"More Game Rules","enabled":true,"position":2,"steamId":"2216850785"},{"displayName":"Extended Outliner","enabled":true,"position":3,"steamId":"2219611817"},{"displayName":"Men-At-Arms Manager","enabled":true,"position":4,"steamId":"3580440930"},{"displayName":"Knight Manager Continued","enabled":true,"position":5,"steamId":"2974850904"},{"displayName":"Patrum Scuta","enabled":true,"position":6,"steamId":"2877995588"},{"displayName":"Auto Repair Artifacts - 1.18","enabled":true,"position":7,"steamId":"3379283577"},{"displayName":"Search & Trade Artifacts","enabled":true,"position":8,"steamId":"2962238514"},{"displayName":"Artifact Manager","enabled":true,"position":9,"steamId":"2886417277"},{"displayName":"Unique Artifacts + (UPDATED 1.18)","enabled":true,"position":10,"steamId":"3603454839"},{"displayName":"Artifacts Variation II","enabled":true,"position":11,"steamId":"3603455041"},{"displayName":"Artifacts of Myth","enabled":true,"position":12,"steamId":"3481270592"},{"displayName":"Community Flavor Pack","enabled":true,"position":13,"steamId":"2220098919"},{"displayName":"Advanced Character Search","enabled":true,"position":14,"steamId":"3084203091"},{"displayName":"More Character Names","enabled":true,"position":15,"steamId":"3451288368"},{"displayName":"More Traditions v2","enabled":true,"position":16,"steamId":"2893793966"},{"displayName":"ARY NEW Traditions","enabled":true,"position":17,"steamId":"3241130652"},{"displayName":"ARY NEW Commander","enabled":true,"position":18,"steamId":"3346529441"},{"displayName":"Chat GPT Flavor Pack | 1.18","enabled":true,"position":19,"steamId":"3122170466"},{"displayName":"Chat GPT Flavor Pack (Unbalance)","enabled":true,"position":20,"steamId":"3598963862"},{"displayName":"Enhanced Dynasty Tree Viewer","enabled":true,"position":21,"steamId":"2427934113"},{"displayName":"Better Mass Vassal Directive","enabled":true,"position":22,"steamId":"3378093812"},{"displayName":"More Interactive Vassals","enabled":true,"position":23,"steamId":"2712590542"},{"displayName":"Population Control (Reduce late-game lag)","enabled":true,"position":24,"steamId":"2276469612"},{"displayName":"[RIT]Simple Manager - Auto-Appoint Vassal Successor（自动任命封臣继任者）","enabled":true,"position":25,"steamId":"3459041118"},{"displayName":"Immersive Holdings","enabled":true,"position":26,"steamId":"3586087462"},{"displayName":"Holding Manager Continued","enabled":true,"position":27,"steamId":"3473706726"},{"displayName":"Architect of Wonders","enabled":true,"position":28,"steamId":"3019391056"},{"displayName":"Architect of Wonders: East Asian Special Buildings Pack","enabled":true,"position":29,"steamId":"3595279885"},{"displayName":"Zeitgeist: Situation & Struggle","enabled":true,"position":30,"steamId":"3571438676"},{"displayName":"Immersive Realm Laws","enabled":true,"position":31,"steamId":"3351630685"},{"displayName":"Traditional Tenets","enabled":true,"position":32,"steamId":"2461889586"},{"displayName":"Multilingual Education","enabled":true,"position":33,"steamId":"2756456587"},{"displayName":"Be Exalted to create Cadet Branch","enabled":true,"position":34,"steamId":"2278502953"},{"displayName":"Pervasive Crown Authority","enabled":true,"position":35,"steamId":"2692957667"},{"displayName":"Houses Traditions","enabled":true,"position":36,"steamId":"2590650832"},{"displayName":"[LOT] Legitimacy Over Time","enabled":true,"position":37,"steamId":"3305687550"},{"displayName":"Unrestricted Legacies","enabled":true,"position":38,"steamId":"3355882108"},{"displayName":"VIET Events - A Flavor and Immersion Event Mod","enabled":true,"position":39,"steamId":"2227658180"},{"displayName":"Lulu's Events","enabled":true,"position":40,"steamId":"2259464577"},{"displayName":"Quando Sumus - Decisions of CK3","enabled":true,"position":41,"steamId":"2818339011"},{"displayName":"Royal Court Event Pack","enabled":true,"position":42,"steamId":"3360676953"},{"displayName":"ENFP's Event Packs","enabled":true,"position":43,"steamId":"3541565115"},{"displayName":"Blood Court: Torturer’s Requiem (1.18)","enabled":true,"position":44,"steamId":"3607155751"},{"displayName":"Love Marriage Family","enabled":true,"position":45,"steamId":"3037969445"},{"displayName":"Found University","enabled":true,"position":46,"steamId":"3465223556"},{"displayName":"More Lifestyles","enabled":true,"position":47,"steamId":"3013259695"},{"displayName":"Witch Trials","enabled":true,"position":48,"steamId":"3007172423"},{"displayName":"Historic Invasions","enabled":true,"position":49,"steamId":"2837398670"},{"displayName":"Active Courtiers","enabled":true,"position":50,"steamId":"3157170996"},{"displayName":"Historicity","enabled":true,"position":51,"steamId":"3107648868"},{"displayName":"[FSF] Browse the Bookstore","enabled":true,"position":52,"steamId":"2751980550"},{"displayName":"A New Sensible Family 3","enabled":true,"position":53,"steamId":"3045026915"},{"displayName":"More Family Relations","enabled":true,"position":54,"steamId":"3469083788"},{"displayName":"SRE Updated 1.18","enabled":true,"position":55,"steamId":"3609156858"},{"displayName":"Take A Bath","enabled":true,"position":56,"steamId":"3118665598"},{"displayName":"Travelers","enabled":true,"position":57,"steamId":"3082182371"},{"displayName":"Better Ruler Designer","enabled":true,"position":58,"steamId":"3275318194"},{"displayName":"Dynasty Bloodline Tracker","enabled":true,"position":59,"steamId":"2824611328"},{"displayName":"Court Alchemist","enabled":true,"position":60,"steamId":"3548614933"},{"displayName":"Court Herbalist","enabled":true,"position":61,"steamId":"3571752592"},{"displayName":"Immersive Domain Management","enabled":true,"position":62,"steamId":"3604729196"},{"displayName":"Incompetent court positions notifications","enabled":true,"position":63,"steamId":"3366606468"},{"displayName":"Quartermaster Court Position","enabled":true,"position":64,"steamId":"3553191520"},{"displayName":"Better Barbershop","enabled":true,"position":65,"steamId":"2220326926"},{"displayName":"Traits Affect Appearance","enabled":true,"position":66,"steamId":"3198429784"},{"displayName":"Visible Disfigurement - No More Masks","enabled":true,"position":67,"steamId":"3245958435"},{"displayName":"Ambush Your Enemy","enabled":true,"position":68,"steamId":"3437183665"},{"displayName":"Auto conversion","enabled":true,"position":69,"steamId":"2694172949"},{"displayName":"Auto increase control","enabled":true,"position":70,"steamId":"2729685999"},{"displayName":"Auto promote culture","enabled":true,"position":71,"steamId":"2689410555"},{"displayName":"Attempt to Convert Anyone","enabled":true,"position":72,"steamId":"3337743548"},{"displayName":"Councillor's experience trait","enabled":true,"position":73,"steamId":"2721974781"},{"displayName":"Donner un surnom","enabled":true,"position":74,"steamId":"3035543804"},{"displayName":"Employ Landless Adventurer","enabled":true,"position":75,"steamId":"3442769560"},{"displayName":"Exam First Rank","enabled":true,"position":76,"steamId":"3597419576"},{"displayName":"Force in acclaimed knight","enabled":true,"position":77,"steamId":"3215270698"},{"displayName":"House Career Manager","enabled":true,"position":78,"steamId":"3597022985"},{"displayName":"I Want Shieldmaiden","enabled":true,"position":79,"steamId":"3479313534"},{"displayName":"Immersive Chaste Trait","enabled":true,"position":80,"steamId":"2662352702"},{"displayName":"Immersive Personalities","enabled":true,"position":81,"steamId":"3596393244"},{"displayName":"Imperial Guards","enabled":true,"position":82,"steamId":"3595280210"},{"displayName":"Improved Witchcraft","enabled":true,"position":83,"steamId":"3566312539"},{"displayName":"Infinite Wards","enabled":true,"position":84,"steamId":"2217801870"},{"displayName":"More Regional Men-at-Arms","enabled":true,"position":85,"steamId":"3567954900"},{"displayName":"More Single Combats","enabled":true,"position":86,"steamId":"2510732954"},{"displayName":"Worthy Conquerors","enabled":true,"position":87,"steamId":"3357686271"},{"displayName":"Lucky Characters","enabled":true,"position":88,"steamId":"2850432978"},{"displayName":"Mass Demand Conversion","enabled":true,"position":89,"steamId":"2753176859"},{"displayName":"Modify Vassal Contract","enabled":true,"position":90,"steamId":"2779619112"},{"displayName":"More Frequent Hunts and Feasts","enabled":true,"position":91,"steamId":"3173792687"},{"displayName":"Battle Graphics","enabled":true,"position":92,"steamId":"3225355262"},{"displayName":"RUI:Character Unofficial","enabled":true,"position":93,"steamId":"3239002020"},{"displayName":"Battleground Commanders","enabled":true,"position":94,"steamId":"3276373926"},{"displayName":"Immersive Mercs & Raiders","enabled":true,"position":95,"steamId":"3461530706"},{"displayName":"War Master","enabled":true,"position":96,"steamId":"3374505712"},{"displayName":"Historical Accuracy","enabled":true,"position":97,"steamId":"2223544446"},{"displayName":"Petty Inheritable Traits","enabled":true,"position":98,"steamId":"2394747105"},{"displayName":"[FSF] Positive Giant Trait","enabled":true,"position":99,"steamId":"2654374260"},{"displayName":"[FSF] Positive Albino Trait","enabled":true,"position":100,"steamId":"2657499830"},{"displayName":"Sons of Ragnar Trait","enabled":true,"position":101,"steamId":"3506287237"},{"displayName":"All Lifestyle Event","enabled":true,"position":102,"steamId":"2221620244"},{"displayName":"fix decisions tab performance","enabled":true,"position":103,"steamId":"3478668605"},{"displayName":"Found Custom Hegemony","enabled":true,"position":104,"steamId":"3598040150"},{"displayName":"Expand Hegemony","enabled":true,"position":105,"steamId":"3605725209"},{"displayName":"Les artisans créent de meilleurs artefacts","enabled":true,"position":106,"steamId":"2875403237"},{"displayName":"Corruption & Trading under the Celestial government","enabled":true,"position":107,"steamId":"3596263413"},{"displayName":"Field Artillery Updated 1.18*","enabled":true,"position":108,"steamId":"3549312874"},{"displayName":"Rise of the Samurai - Japanese MAA expansion","enabled":true,"position":109,"steamId":"3597329187"},{"displayName":"Recruitable Order Knights","enabled":true,"position":110,"steamId":"2782626004"},{"displayName":"Recruitable Jomsviking Pirates","enabled":true,"position":111,"steamId":"2779427014"},{"displayName":"Duel Overlay","enabled":true,"position":112,"steamId":"2636170225"},{"displayName":"Clear Notifications","enabled":true,"position":113,"steamId":"2261468688"},{"displayName":"Commander+ (UPDATED 1.18)","enabled":true,"position":114,"steamId":"3603454649"},{"displayName":"Invite Characters","enabled":true,"position":115,"steamId":"3603563862"},{"displayName":"Deadly Sieges and Raids","enabled":true,"position":116,"steamId":"3608990599"},{"displayName":"Wandering XP from Wandering","enabled":true,"position":117,"steamId":"3360461641"},{"displayName":"Big Battle View","enabled":true,"position":118,"steamId":"3030427202"},{"displayName":"Play as heir anytime","enabled":true,"position":119,"steamId":"3599140060"},{"displayName":"Dark Ages","enabled":true,"position":120,"steamId":"2975514448"}]}